freecodecamp_reader/__init__.py
freecodecamp_reader/cli.py
freecodecamp_reader/parser.py
tests/__init__.py
freecodecamp_reader-0.1.1.dist-info/METADATA
freecodecamp_reader-0.1.1.dist-info/WHEEL
freecodecamp_reader-0.1.1.dist-info/top_level.txt
freecodecamp_reader-0.1.1.dist-info/RECORD
