Metadata-Version: 2.1
Name: freecodecamp-reader
Version: 0.1.1
Summary: A package to fetch and display the latest tutorials from FreeCodeCamp.
Home-page: https://github.com/Devin-Apps/Freecodecamp-reader
Author: Devin
Author-email: devin@example.com
License: UNKNOWN
Platform: UNKNOWN
Classifier: Programming Language :: Python :: 3
Classifier: License :: OSI Approved :: MIT License
Classifier: Operating System :: OS Independent
Requires-Python: >=3.6
Requires-Dist: beautifulsoup4 (>=4.9.3)
Requires-Dist: requests (>=2.23.0)
